nonebot_plugin_jx3/__init__.py
nonebot_plugin_jx3/bind.py
nonebot_plugin_jx3/config.py
nonebot_plugin_jx3/help.png
nonebot_plugin_jx3/subscribe.py
nonebot_plugin_jx3/userdefine.py
nonebot_plugin_jx3/websocket_handler.py
nonebot_plugin_jx3-0.7.dist-info/LICENSE
nonebot_plugin_jx3-0.7.dist-info/METADATA
nonebot_plugin_jx3-0.7.dist-info/WHEEL
nonebot_plugin_jx3-0.7.dist-info/RECORD
