Metadata-Version: 2.1
Name: nonebot-plugin-jx3
Version: 0.7
Summary: 一个nonebot2的jx3插件
Home-page: https://github.com/fuyang0811/nonebot-plugin-jx3
License: MIT
Author: water
Author-email: 415276785@qq.com
Requires-Python: >=3.8,<4.0
Classifier: License :: OSI Approved :: MIT License
Classifier: Programming Language :: Python :: 3
Classifier: Programming Language :: Python :: 3.8
Classifier: Programming Language :: Python :: 3.9
Classifier: Programming Language :: Python :: 3.10
Classifier: Programming Language :: Python :: 3.11
Requires-Dist: aiohttp (>=3.7.4,<4.0.0)
Requires-Dist: httpx (>=0.19.0,<0.20.0)
Requires-Dist: nonebot-adapter-onebot (>=2.0.0,<3.0.0)
Requires-Dist: nonebot2 (>=2.0.0rc1,<3.0.0)
Requires-Dist: nonebot_plugin_apscheduler (>=0.3.0,<0.4.0)
Requires-Dist: tinydb (>=4.5.1,<5.0.0)
